epifx/__init__.py
epifx/det.py
epifx/model.py
epifx/obs.py
epifx/select.py
epifx/stoch.py
epifx/summary.py
epifx/cmd/__init__.py
epifx/cmd/_parser.py
epifx/cmd/forecast.py
epifx/example/__init__.py
epifx/example/seir/__init__.py
epifx/example/seir/pr-obs-scalar.ssv
epifx/example/seir/pr-obs.ssv
epifx/example/seir/seeiir.toml
epifx/example/seir/seeiir_scalar.toml
epifx/example/seir/seir.py
epifx/example/seir/seir.toml
epifx/example/seir/seir_quick.toml
epifx/example/seir/stoch.toml
epifx/example/seir/weekly-cases-quick.ssv
epifx/example/seir/weekly-cases-scalar.ssv
epifx/example/seir/weekly-cases.ssv
epifx-0.8.2.dist-info/METADATA
epifx-0.8.2.dist-info/WHEEL
epifx-0.8.2.dist-info/entry_points.txt
epifx-0.8.2.dist-info/licenses/LICENSE
epifx-0.8.2.dist-info/RECORD
