Metadata-Version: 2.4
Name: epifx
Version: 0.8.2
Summary: Epidemic forecasting with mechanistic infection models
Project-URL: homepage, https://bitbucket.org/robmoss/epidemic-forecasting-for-python/
Project-URL: repository, https://bitbucket.org/robmoss/epidemic-forecasting-for-python/
Project-URL: documentation, https://epifx.readthedocs.io/en/latest/
Project-URL: changelog, https://epifx.readthedocs.io/en/latest/changelog.html
Author-email: Rob Moss <rgmoss@unimelb.edu.au>
Maintainer-email: Rob Moss <rgmoss@unimelb.edu.au>
License: Copyright (c) 2014-2025, Rob Moss
License-File: LICENSE
Classifier: Development Status :: 4 - Beta
Classifier: Intended Audience :: Science/Research
Classifier: License :: OSI Approved :: BSD License
Classifier: Operating System :: OS Independent
Classifier: Programming Language :: Python
Classifier: Programming Language :: Python :: 3
Classifier: Topic :: Scientific/Engineering :: Mathematics
Requires-Python: >=3.8
Requires-Dist: h5py~=3.0
Requires-Dist: numpy>=1.17
Requires-Dist: parq~=0.2
Requires-Dist: pypfilt~=0.8.1
Requires-Dist: scipy~=1.4
